airtable_db_export/__init__.py
airtable_db_export/__main__.py
airtable_db_export/at.py
airtable_db_export/db.py
airtable_db_export/main.py
airtable_db_export/utils.py
airtable_db_export-0.4.2.dist-info/METADATA
airtable_db_export-0.4.2.dist-info/WHEEL
airtable_db_export-0.4.2.dist-info/entry_points.txt
airtable_db_export-0.4.2.dist-info/licenses/LICENSE.md
airtable_db_export-0.4.2.dist-info/RECORD
