Metadata-Version: 2.4
Name: airtable-db-export
Version: 0.4.2
Summary: Download data from Airtable to a SQL database.
Author-email: Steve Ivy <steveivy@gmail.com>
License-File: LICENSE.md
Requires-Python: >=3.12
Requires-Dist: click>=8.1.8
Requires-Dist: duckdb>=1.3.0
Requires-Dist: pandas>=2.2.3
Requires-Dist: pyairtable>=3.1.1
Requires-Dist: python-dotenv>=1.1.0
Requires-Dist: pyyaml>=6.0.2
